{
    "index": {
        "get": {
            "tags": [
                "ordertypes"
            ],
            "summary": "Find all of the order types",
            "description": "Find all of the order types, it will return an array with order type entries containing an identifier, a boolean if the order type is currently deleted and the last modified date/time in local time",
            "produces": "application/json",
            "parameters": [ ],
            "responses": {
                "200": {
                    "description": "A list of ordertypes.",
                    "schema": {
                        "$ref": "../definitions.json#/definitions/OrderTypesResponse"
                    }
                }
            }
        }
    }
}